ncuploader/__init__.py
ncuploader/cli.py
ncuploader/config.py
ncuploader/index.py
ncuploader/retention.py
ncuploader/uploader.py
ncuploader-0.2.1.dist-info/METADATA
ncuploader-0.2.1.dist-info/WHEEL
ncuploader-0.2.1.dist-info/entry_points.txt
ncuploader-0.2.1.dist-info/RECORD
