Metadata-Version: 2.4
Name: ncuploader
Version: 0.2.1
Summary: A CLI tool to upload files and directories to Nextcloud with support for retention policies, dry-run, and tilde expansion for local paths.
Project-URL: Homepage, https://gitverse.ru/avkolupaev/ncuploader
Author-email: NCUploader Authors <a.v.kolupaev@ya.ru>
License: MIT
Classifier: License :: OSI Approved :: MIT License
Classifier: Operating System :: OS Independent
Classifier: Programming Language :: Python :: 3
Classifier: Programming Language :: Python :: 3.12
Classifier: Topic :: System :: Archiving :: Backup
Classifier: Topic :: Utilities
Requires-Python: >=3.12
Requires-Dist: loguru>=0.7.3
Requires-Dist: nc-py-api>=0.20.1
Requires-Dist: pydantic>=2.11.4
Requires-Dist: python-dotenv>=1.1.0
Requires-Dist: pyyaml>=6.0.2
Requires-Dist: requests>=2.32.3
Requires-Dist: rich>=14.0.0
Requires-Dist: typer>=0.15.3
